nodefinder/__init__.py
nodefinder/_common_plot.py
nodefinder/_logging.py
nodefinder/coordinate_system.py
nodefinder/io.py
nodefinder/identify/__init__.py
nodefinder/identify/_cluster.py
nodefinder/identify/_dimension.py
nodefinder/identify/_logging.py
nodefinder/identify/_run.py
nodefinder/identify/plot.py
nodefinder/identify/_evaluate/__init__.py
nodefinder/identify/_evaluate/_point.py
nodefinder/identify/_evaluate/_run.py
nodefinder/identify/_evaluate/_line/__init__.py
nodefinder/identify/_evaluate/_line/_ballistic.py
nodefinder/identify/_evaluate/_line/_dominating_set.py
nodefinder/identify/_evaluate/_line/_run.py
nodefinder/identify/_evaluate/_line/_shortest_path.py
nodefinder/identify/result/__init__.py
nodefinder/identify/result/_containers.py
nodefinder/identify/result/_shapes.py
nodefinder/search/__init__.py
nodefinder/search/_controller.py
nodefinder/search/_fake_potential.py
nodefinder/search/_logging.py
nodefinder/search/_mesh_helper.py
nodefinder/search/_queue.py
nodefinder/search/_run.py
nodefinder/search/plot.py
nodefinder/search/refinement_stencil.py
nodefinder/search/_minimization/__init__.py
nodefinder/search/_minimization/_nelder_mead.py
nodefinder/search/_minimization/_run.py
nodefinder/search/result/__init__.py
nodefinder/search/result/_cell_list.py
nodefinder/search/result/_controller_state.py
nodefinder/search/result/_minimization.py
nodefinder/search/result/_search_result_container.py
nodefinder-0.1.2.dist-info/METADATA
nodefinder-0.1.2.dist-info/WHEEL
nodefinder-0.1.2.dist-info/entry_points.txt
nodefinder-0.1.2.dist-info/licenses/LICENSE.txt
nodefinder-0.1.2.dist-info/RECORD
