Metadata-Version: 2.4
Name: nodefinder
Version: 0.1.2
Summary: A tool for studying the nodal features of potential lanscapes.
Project-URL: documentation, https://nodefinder.greschd.ch
Project-URL: repository, https://github.com/greschd/NodeFinder
Author-email: Dominik Gresch <mail@greschd.ch>
License:                                  Apache License
License-File: LICENSE.txt
Keywords: minimization,node search
Classifier: Development Status :: 4 - Beta
Classifier: Intended Audience :: Science/Research
Classifier: License :: OSI Approved :: Apache Software License
Classifier: Natural Language :: English
Classifier: Operating System :: Unix
Classifier: Programming Language :: Python :: 3
Classifier: Programming Language :: Python :: 3.7
Classifier: Programming Language :: Python :: 3.8
Classifier: Programming Language :: Python :: 3.9
Classifier: Programming Language :: Python :: 3.10
Classifier: Programming Language :: Python :: 3.11
Classifier: Programming Language :: Python :: 3.12
Classifier: Programming Language :: Python :: 3.13
Classifier: Topic :: Scientific/Engineering :: Physics
Requires-Python: >=3.9
Requires-Dist: decorator>=5.1.1
Requires-Dist: fsc-async-tools>=0.3.0
Requires-Dist: fsc-export>=1.2.0
Requires-Dist: fsc-hdf5-io>=1.0.3
Requires-Dist: matplotlib>=3.5.3
Requires-Dist: networkx>=2.6.3
Requires-Dist: numpy>=1.21.6
Requires-Dist: scipy>=1.7.3
